django_data_tables/__init__.py
django_data_tables/apps.py
django_data_tables/column.py
django_data_tables/filter.py
django_data_tables/table.py
django_data_tables/utils.py
django_data_tables/views.py
django_data_tables/static/django_data_tables/.django_data_tables.css.swp
django_data_tables/static/django_data_tables/django_data_tables.css
django_data_tables/static/django_data_tables/django_data_tables.js
django_data_tables/templates/django_data_tables/action_column.html
django_data_tables/templates/django_data_tables/django_data_table.html
django_data_tables/templatetags/__init__.py
django_data_tables/templatetags/data_table_render_column.py
django_data_tables-0.4.2.dist-info/LICENSE
django_data_tables-0.4.2.dist-info/METADATA
django_data_tables-0.4.2.dist-info/WHEEL
django_data_tables-0.4.2.dist-info/top_level.txt
django_data_tables-0.4.2.dist-info/RECORD
